<?xml version="1.0" encoding="utf-8"?>
<Entity parent="template_structure_special">
  <Cost>
    <BuildTime>200</BuildTime>
    <Resources>
      <stone>200</stone>
      <metal>200</metal>
    </Resources>
  </Cost>
  <Footprint>
    <Square width="28" depth="12.0"/>
    <Height>10.0</Height>
  </Footprint>
  <Identity>
    <Civ>maur</Civ>
    <Classes datatype="tokens">ConquestCritical</Classes>
    <SpecificName>Harmya</SpecificName>
    <VisibleClasses datatype="tokens">
	  -City
	  Village
	  Palace
	</VisibleClasses>
    <GenericName>Palace</GenericName>
    <Icon>structures/maur_palace.png</Icon>
    <Tooltip>Train Heroes and Maiden Archers.</Tooltip>
    <Undeletable>true</Undeletable>
  </Identity>
  <Loot>
    <stone>40</stone>
    <metal>40</metal>
  </Loot>
  <Obstruction>
    <Static width="26.0" depth="10.5"/>
  </Obstruction>
  <ProductionQueue>
    <BatchTimeModifier>0.7</BatchTimeModifier>
    <Entities datatype="tokens">
      units/maur/champion_maiden
      units/maur/hero_chanakya
      units/maur/hero_chandragupta_infantry
      units/maur/hero_ashoka_infantry
    </Entities>
  </ProductionQueue>
  <TerritoryInfluence>
    <Root>false</Root>
    <Radius>38</Radius>
    <Weight>65535</Weight>
  </TerritoryInfluence>
  <VisualActor>
    <Actor>structures/mauryas/misc_structure_01.xml</Actor>
  </VisualActor>
</Entity>
