{
	"genericName": "Antiochus IV the Glorious",
	"description": "Antiochus IV the Glorious.",
	"icon": "sele_hero_antiochus_IV_card.png",
	"tooltip": "Select Antiochus IV to lead your civilization.",
	"modifications": [
		{
			"value": "ProductionQueue/Entities/_string",
			"tokens": "-units/{civ}_hero_seleucus_victor_infantry -units/{civ}_hero_antiochus_great_infantry",
			"affects": "CivilCentre"
		},
		{
			"value": "Builder/Entities/_string",
			"tokens": "-structures/{civ}_civil_centre structures/mace_theater",
			"affects": "Builder"
		}
	]
}
