<?xml version="1.0" encoding="utf-8"?>
<Entity parent="template_unit_mercenary_infantry_melee_spearman">
  <Builder>
	<Entities datatype="tokens">
    </Entities>
  </Builder>
  <Cost>
    <Population>1</Population>
  </Cost>
  <Identity>
    <Civ>imp</Civ>
	<Lang>latin</Lang>
    <GenericName>Auxiliary Spearman</GenericName>
    <SpecificName>Pedites Auxiliares</SpecificName>
    <VisibleClasses datatype="tokens">
	  Auxiliary
	</VisibleClasses>
    <Icon>units/imp_merc_spearman.png</Icon>
  </Identity>
  <TrainingRestrictions>
    <Category>Auxilia</Category>
  </TrainingRestrictions>
  <VisualActor>
    <Actor>units/romans_imperial/infantry_spearman.xml</Actor>
  </VisualActor>
</Entity>