<?xml version="1.0" encoding="utf-8"?>
<Entity parent="units/mace_champion_infantry_a">
  <Armour>
    <Hack op="add">1</Hack>
    <Pierce op="add">1</Pierce>
    <Crush op="add">1</Crush>
  </Armour>
  <Attack>
    <Melee>
      <Hack op="mul">1.1</Hack>
    </Melee>
  </Attack>
  <Health>
    <Max op="mul">1.1</Max>
  </Health>
  <Identity>
	<GenericName>Silver Shield Guardsman</GenericName>
    <SpecificName>Hypaspistès Argyraspídi</SpecificName>
    <Icon>units/macedonian_argyraspidai.png</Icon>
	<SelectionGroupName>units/mace_champion_infantry_e</SelectionGroupName>
  </Identity>
  <Upgrade disable=""/>
  <VisualActor>
    <Actor>units/macedonians/champion_infantry_e.xml</Actor>
  </VisualActor>
</Entity>