<?xml version="1.0" encoding="utf-8"?>
<actor version="1">
  <castshadow/>
  <group>
    <variant frequency="1" name="Cretan-Date-Palm-Patch-01">
      <props>
        <prop actor="props/flora/decal_palms_patch.xml" attachpoint="root"/>
      </props>
    </variant>
  </group>
  <group>
    <variant frequency="1" name="Model High Poly">
      <mesh>gaia/tree_cretan_date_palm_patch_01.dae</mesh>
    </variant>
    <variant frequency="1" name="Model Low Poly">
      <mesh>gaia/tree_cretan_date_palm_patch_01_low.dae</mesh>
    </variant>
  </group>
  <group>
    <variant frequency="1" name="Patch-Palm Fronds-a">
      <textures>
        <texture file="gaia/tree_palm_senegal_a.dds" name="baseTex"/>
        <texture file="gaia/tree_palm_senegal_spec.png" name="specTex"/>
        <texture file="gaia/tree_palm_senegal_norm.png" name="normTex"/>
      </textures>
    </variant>
    <variant frequency="1" name="Patch-Palm Fronds-b">
      <textures>
        <texture file="gaia/tree_palm_senegal_b.dds" name="baseTex"/>
        <texture file="gaia/tree_palm_senegal_spec.png" name="specTex"/>
        <texture file="gaia/tree_palm_senegal_norm.png" name="normTex"/>
      </textures>
    </variant>
    <variant frequency="1" name="Patch-Palm Fronds-c">
      <textures>
        <texture file="gaia/tree_palm_senegal_c.dds" name="baseTex"/>
        <texture file="gaia/tree_palm_senegal_spec.png" name="specTex"/>
        <texture file="gaia/tree_palm_senegal_norm.png" name="normTex"/>
      </textures>
    </variant>
    <variant frequency="1" name="Patch-Palm Fronds-d">
      <textures>
        <texture file="gaia/tree_palm_senegal_d.dds" name="baseTex"/>
        <texture file="gaia/tree_palm_senegal_spec.png" name="specTex"/>
        <texture file="gaia/tree_palm_senegal_norm.png" name="normTex"/>
      </textures>
    </variant>
  </group>
  <material>basic_trans_wind_norm_spec.xml</material>
</actor>
