{
	"civ": "mace",
	"type": "player",
	"affects": ["Player"],
	"affectedPlayers": ["ExclusiveMutualAlly"],
	"modifications": [
		{ "value": "Player/BarterMultiplier/Sell/food", "multiply": 1.2 },
		{ "value": "Player/BarterMultiplier/Sell/wood", "multiply": 1.2 },
		{ "value": "Player/BarterMultiplier/Sell/stone", "multiply": 1.2 },
		{ "value": "Player/BarterMultiplier/Sell/metal", "multiply": 1.2 },
		{ "value": "Player/BarterMultiplier/Sell/coin", "multiply": 1.2 }
	],
	"auraName": "Standardized Currency",
	"auraDescription": "Selling resources at the Market +20% profit.",
	"description":"The Macedonians and the Diadochi minted coins of very high quality. On their currency the Diadochi in particular frequently depicted themselves as the rightful successor to Alexander the Great, attempting to legitimize their rule."
}
