<?xml version="1.0" encoding="utf-8"?>
<Entity parent="template_structure_military_blacksmith">
  <Cost>
    <PopulationBonus>2</PopulationBonus>
  </Cost>
  <Footprint replace="">
    <Circle radius="16.0"/>
    <Height>8.0</Height>
  </Footprint>
  <ProductionQueue>
    <BatchTimeModifier>0.8</BatchTimeModifier>
    <Entities datatype="tokens">
      units/xion_support_wagon
    </Entities>
    <Technologies datatype="tokens">
      unlock_champion_units_xion
    </Technologies>
  </ProductionQueue>
  <BuildRestrictions>
    <Territory>own neutral ally</Territory>
  </BuildRestrictions>
  <Upgrade>
    <BlacksmithPacked>
      <Entity>structures/xion_blacksmith_packed</Entity>
      <Time>20</Time>
    </BlacksmithPacked>
  </Upgrade>
  <Identity>
    <Civ>xion</Civ>
  </Identity>
  <Obstruction>
    <Static width="25.0" depth="25.0"/>
  </Obstruction>
  <TerritoryDecay disable=""/>
  <TerritoryInfluence disable=""/>
  <VisualActor>
    <ConstructionPreview disable=""/>
    <Actor>structures/xiongnu/blacksmith.xml</Actor>
    <FoundationActor>structures/xiongnu/blacksmith_foundation.xml</FoundationActor>
  </VisualActor>
</Entity>
