<?xml version="1.0" encoding="utf-8"?>
<Entity parent="template_structure_resource_corral">
  <Footprint>
    <Square width="13.0" depth="17.0"/>
    <Height>8.0</Height>
  </Footprint>
  <Health>
    <SpawnEntityOnDeath>decay|rubble/rubble_stone_3x3</SpawnEntityOnDeath>
  </Health>
  <Identity>
    <Civ>zapo</Civ>
  <GenericName>Corral</GenericName>
    <SpecificName>Kúuchil</SpecificName>
  </Identity>
  <Obstruction>
    <Static width="10.0" depth="14.0"/>
  </Obstruction>
  <ProductionQueue>
    <Technologies datatype="tokens">
    </Technologies>
  </ProductionQueue>
  <VisualActor>
    <Actor>structures/zapotecs/corral.xml</Actor>
    <FoundationActor>structures/fndn_3x3.xml</FoundationActor>
  </VisualActor>
</Entity>
