<?xml version="1.0" encoding="utf-8"?>
<actor version="1">
  <castshadow/>
  <group>
    <variant frequency="33" name="Goth House A">
      <mesh>structural/goths/house_a.dae</mesh>
      <textures>
        <texture file="structural/goth_struct.png" name="baseTex"/>
        <texture file="structural/goth_struct_norm.png" name="normTex"/>
        <texture file="structural/goth_struct_spec.png" name="specTex"/>
        <texture file="structural/ao/goth_house_a_ao.png" name="aoTex"/>
      </textures>
      <props>
        <prop actor="props/structures/goths/barrel.xml" attachpoint="barrel_1"/>
        <prop actor="props/structures/goths/barrel.xml" attachpoint="barrel_2"/>
        <prop actor="props/structures/goths/barrel.xml" attachpoint="barrel_3"/>
        <prop actor="props/structures/decals/dirt_3x3.xml" attachpoint="root"/>
        <prop actor="props/structures/goths/fence_b_medium.xml" attachpoint="fence_medium_a"/>
        <prop actor="props/structures/goths/fence_b_short.xml" attachpoint="fence_short_a"/>
        <prop actor="props/structures/goths/fence_a_short.xml" attachpoint="fence_short_b"/>
        <prop actor="props/structures/goths/fence_a_short.xml" attachpoint="fence_short_c"/>
        <prop actor="props/structures/goths/fence_b_short.xml" attachpoint="fence_short_d"/>
        <prop actor="props/structures/goths/fence_b_medium.xml" attachpoint="fence_short_e"/>
        <prop actor="props/structures/goths/fence_a_short.xml" attachpoint="fence_short_f"/>
        <prop actor="props/structures/goths/fence_b_short.xml" attachpoint="fence_short_g"/>
        <prop actor="props/structures/goths/fence_a_short.xml" attachpoint="fence_short_h"/>
        <prop actor="props/structures/goths/fence_a_short.xml" attachpoint="fence_short_i"/>
        <prop actor="props/structures/goths/fence_a_short.xml" attachpoint="fence_short_j"/>
        <prop actor="props/structures/goths/fence_b_short.xml" attachpoint="fence_short_k"/>
        <prop actor="props/structures/goths/basket_a.xml" attachpoint="basket_b"/>
        <prop actor="props/structures/goths/basket_b.xml" attachpoint="basket_a"/>
        <prop actor="props/structures/goths/basket_c.xml" attachpoint="basket_c"/>
        <prop actor="props/structures/goths/table.xml" attachpoint="table"/>
        <prop actor="props/structures/goths/skin.xml" attachpoint="skin"/>
        <prop actor="props/structures/goths/shelf.xml" attachpoint="shelf"/>
        <prop actor="particle/smoke_curved.xml" attachpoint="smoke"/>
        <prop actor="props/units/weapons/arrow_front.xml" attachpoint="projectile"/>
        <prop actor="props/special/eyecandy/sack_1.xml" attachpoint="sack_1"/>
        <prop actor="props/special/eyecandy/sack_1.xml" attachpoint="sack_2"/>
      </props>
    </variant>
    <variant frequency="33" name="Goth House B">
      <mesh>structural/goths/house_b.dae</mesh>
      <textures>
        <texture file="structural/goth_struct.png" name="baseTex"/>
        <texture file="structural/goth_struct_norm.png" name="normTex"/>
        <texture file="structural/goth_struct_spec.png" name="specTex"/>
        <texture file="structural/ao/goth_house_b_ao.png" name="aoTex"/>
      </textures>
      <props>
        <prop actor="props/special/eyecandy/crate_a.xml" attachpoint="crate_a"/>
        <prop actor="props/special/eyecandy/crate_a.xml" attachpoint="crate_b"/>
        <prop actor="props/units/weapons/norse_axe.xml" attachpoint="axe_a"/>
        <prop actor="props/units/weapons/norse_axe.xml" attachpoint="axe_b"/>
        <prop actor="props/structures/goths/barrel.xml" attachpoint="barrel_a"/>
        <prop actor="props/structures/goths/barrel.xml" attachpoint="barrel_b"/>
        <prop actor="props/units/shields/norse_ship_shield_b.xml" attachpoint="shield_a"/>
        <prop actor="props/structures/decals/dirt_3x3.xml" attachpoint="root"/>
        <prop actor="props/structures/goths/table.xml" attachpoint="table"/>
        <prop actor="props/structures/goths/fence_b_medium.xml" attachpoint="fence_medium_a"/>
        <prop actor="props/structures/goths/fence_a_medium.xml" attachpoint="fence_medium_b"/>
        <prop actor="props/structures/goths/fence_b_medium.xml" attachpoint="fence_medium_c"/>
        <prop actor="props/structures/goths/fence_b_medium.xml" attachpoint="fence_medium_d"/>
        <prop actor="props/structures/goths/fence_a_medium.xml" attachpoint="fence_medium_e"/>
        <prop actor="props/structures/goths/fence_b_short.xml" attachpoint="fence_short_a"/>
        <prop actor="props/structures/goths/fence_a_short.xml" attachpoint="fence_short_b"/>
        <prop actor="props/structures/goths/fence_b_short.xml" attachpoint="fence_short_c"/>
        <prop actor="props/structures/goths/fence_a_short.xml" attachpoint="fence_short_d"/>
        <prop actor="props/structures/goths/fence_b_short.xml" attachpoint="fence_short_e"/>
        <prop actor="particle/smoke_blacksmith.xml" attachpoint="smoke"/>
        <prop actor="props/units/weapons/arrow_front.xml" attachpoint="projectile"/>
      </props>
    </variant>
    <variant frequency="33" name="Goth House C">
      <mesh>structural/goths/house_c.dae</mesh>
      <textures>
        <texture file="structural/goth_struct.png" name="baseTex"/>
        <texture file="structural/goth_struct_norm.png" name="normTex"/>
        <texture file="structural/goth_struct_spec.png" name="specTex"/>
        <texture file="structural/ao/goth_house_c_ao.png" name="aoTex"/>
      </textures>
      <props>
        <prop actor="props/structures/decals/dirt_3x3.xml" attachpoint="root"/>
        <prop actor="props/structures/goths/barrel.xml" attachpoint="barrel_a"/>
        <prop actor="props/structures/goths/barrel.xml" attachpoint="barrel_b"/>
        <prop actor="props/structures/goths/skin.xml" attachpoint="skin_a"/>
        <prop actor="props/structures/goths/skin.xml" attachpoint="skin_b"/>
        <prop actor="props/structures/goths/fence_b_short.xml" attachpoint="fence_short_a"/>
        <prop actor="props/structures/goths/fence_a_short.xml" attachpoint="fence_short_b"/>
        <prop actor="props/structures/goths/fence_a_short.xml" attachpoint="fence_short_c"/>
        <prop actor="props/structures/goths/fence_b_short.xml" attachpoint="fence_short_d"/>
        <prop actor="props/structures/goths/fence_a_short.xml" attachpoint="fence_short_e"/>
        <prop actor="props/structures/goths/fence_a_short.xml" attachpoint="fence_short_f"/>
        <prop actor="props/structures/goths/fence_b_short.xml" attachpoint="fence_short_g"/>
        <prop actor="props/structures/goths/fence_b_medium.xml" attachpoint="fence_medium_a"/>
        <prop actor="props/structures/goths/fence_a_medium.xml" attachpoint="fence_medium_b"/>
        <prop actor="props/structures/goths/fence_b_medium.xml" attachpoint="fence_medium_c"/>
        <prop actor="props/structures/goths/fence_a_medium.xml" attachpoint="fence_medium_d"/>
        <prop actor="particle/smoke_curved.xml" attachpoint="smoke"/>
        <prop actor="props/units/weapons/arrow_front.xml" attachpoint="projectile"/>
      </props>
    </variant>
  </group>
  <group>
    <variant frequency="1" name="alive"/>
    <variant name="garrisoned">
      <props>
        <prop actor="props/special/common/garrison_flag_germ.xml" attachpoint="garrisoned"/>
      </props>
    </variant>
  </group>
  <group>
    <variant name="alive" frequency="1"/>
    <variant file="structures/destruction_small.xml"/>
  </group>
  <material>player_trans_ao_parallax_spec.xml</material>
</actor>
