<?xml version="1.0" encoding="utf-8"?>
<actor version="1">
  <castshadow/>
  <group>
    <variant>
      <textures>
        <texture file="default_norm.png" name="normTex"/>
        <texture file="null_black.dds" name="specTex"/>
	  </textures>
    </variant>
  </group>
  <group>
    <variant frequency="1" name="s_1">
      <mesh>props/shield/yayoi_s_tedate_a.dae</mesh>
      <textures>
        <texture file="props/shiled_tedate_a_1.png" name="baseTex"/>
      </textures>
    </variant>
        <variant frequency="1" name="s_2">
      <mesh>props/shield/yayoi_s_tedate_a.dae</mesh>
      <textures>
        <texture file="props/shiled_tedate_a_1.png" name="baseTex"/>
      </textures>
    </variant>
  </group>
  <material>player_trans_norm_spec.xml</material>
</actor>
