{
	"pair": "pair_structures_04",
	"genericName": "Monumental Architecture",
	"specificName": {
		"imp": "Architectura Monumentalis"
	},
	"description": "When a civilization reaches a certain size and sophistication, monumental things happen.",
	"cost": {"food": 0, "wood": 0, "stone": 1000, "glory": 500},
	"requirements": {"tech": "phase_imperial"},
	"requirementsTooltip": "Unlocked in Empire Phase.",
	"icon": "monumental_architecture.png",
	"researchTime": 40,
	"tooltip": "All structures +20% health, but +20% build time.",
	"modifications": [
		{"value": "Health/Max", "multiply": 1.2},
		{"value": "Cost/BuildTime", "multiply": 1.2}
	],
	"affects": ["NotField"],
	"soundComplete": "interface/alarm/alarm_upgradearmory.xml"
}
