{
	"genericName": "Elite Citizen Spear Infantry",
	"specificName": {
		"hele": "Zeugites",
		"mace": "Zeugites",
		"spart": "Mothakes",
		"athen": "Zeugites"
	},
	"description": "Upgrade all of your citizen spearmen to Elite rank.",
	"cost": {
		"coin": 600,
		"glory": 600
	},
	"requirements": {
		"all": [
			{ "tech": "phase_empire" },
			{
				"any": [
					{ "civ": "brit" },
					{ "civ": "gaul" },
					{ "civ": "han" },
					{ "civ": "iber" },
					{ "civ": "kush" },
					{ "civ": "maur" },
					{ "civ": "pers" },
					{ "civ": "scyth" },
					{ "civ": "sele" },
					{ "civ": "sueb" },
					{ "civ": "xion" }
				]
			}
		]
	},
	"requirementsTooltip": "Unlocked in Empire Phase. Requires “Advanced Citizen Spear Infantry.”",
	"icon": "upgrade_elite.png",
	"researchTime": 40,
	"supersedes": "upgrade_rank_advanced_infantry_spear",
	"tooltip": "Upgrade all of your Citizen Spear Infantry to Elite rank. This greatly increases their military prowess, but also increases their training costs and training time by +10%.",
	"modifications": [
		{ "value": "Promotion/RequiredXp", "replace": 0 }
	],
	"affects": ["Spear Infantry Advanced"],
	"soundComplete": "interface/alarm/alarm_upgradearmory.xml"
}
