<?xml version="1.0" encoding="utf-8"?>
<actor version="1">
  <castshadow/>
  <group>
    <variant frequency="1" name="Base">
      <mesh>skeletal/new/m_pants_tunic_long.dae</mesh>
      <props>
        <prop actor="props/units/heads/new/head_celt.xml" attachpoint="head"/>
        <prop actor="props/units/weapons/dagger.xml" attachpoint="weapon_R"/>
      </props>
    </variant>
  </group>
  <group>
    <variant frequency="1" name="celt_basic_01">
      <textures><texture file="skeletal/celt_basic_01.png" name="baseTex"/></textures>
    </variant>
    <variant frequency="1" name="celt_basic_02">
      <textures><texture file="skeletal/celt_basic_02.png" name="baseTex"/></textures>
    </variant>
    <variant frequency="1" name="celt_basic_03">
      <textures><texture file="skeletal/celt_basic_03.png" name="baseTex"/></textures>
    </variant>
    <variant frequency="1" name="celt_basic_04">
      <textures><texture file="skeletal/celt_basic_04.png" name="baseTex"/></textures>
    </variant>
    <variant frequency="2" name="celt_basic_05">
      <textures><texture file="skeletal/celt_basic_05.png" name="baseTex"/></textures>
    </variant>
    <variant frequency="1" name="celt_basic_06">
      <textures><texture file="skeletal/celt_basic_06.png" name="baseTex"/></textures>
    </variant>
    <variant frequency="1" name="celt_basic_07">
      <textures><texture file="skeletal/celt_basic_07.png" name="baseTex"/></textures>
    </variant>
    <variant frequency="1" name="celt_basic_08">
      <textures><texture file="skeletal/celt_basic_08.png" name="baseTex"/></textures>
    </variant>
    <variant frequency="1" name="celt_basic_09">
      <textures><texture file="skeletal/celt_basic_09.png" name="baseTex"/></textures>
    </variant>
    <variant frequency="2" name="celt_basic_10">
      <textures><texture file="skeletal/celt_basic_10.png" name="baseTex"/></textures>
    </variant>
    <variant frequency="1" name="celt_basic_11">
      <textures><texture file="skeletal/celt_basic_11.png" name="baseTex"/></textures>
    </variant>
    <variant frequency="1" name="celt_basic_12">
      <textures><texture file="skeletal/celt_basic_12.png" name="baseTex"/></textures>
    </variant>
    <variant frequency="1" name="celt_basic_13">
      <textures><texture file="skeletal/celt_basic_13.png" name="baseTex"/></textures>
    </variant>
    <variant frequency="1" name="celt_basic_14">
      <textures><texture file="skeletal/celt_basic_14.png" name="baseTex"/></textures>
    </variant>
    <variant frequency="1" name="celt_basic_15">
      <textures><texture file="skeletal/celt_wool_01.png" name="baseTex"/></textures>
    </variant>
  </group>
  <group>
    <variant file="biped/rider/cavalry/base_swordsman_fast_relax.xml" frequency="1" name="Swordsman-Fast-Relax"/>
    <variant file="biped/rider/carry_meat.xml"/>
  </group>
  <group>
    <variant frequency="1" name="Idle"/>
    <variant file="biped/rider/promotion.xml"/>
    <variant file="biped/rider/attack_slaughter_hele.xml"/>
    <variant file="biped/gather_meat.xml"/>
    <variant file="biped/rider/death.xml"/>
  </group>
  <material>player_trans.xml</material>
</actor>
